odoo/addons/stock_orderpoint_manual_procurement/README.rst
odoo/addons/stock_orderpoint_manual_procurement/__init__.py
odoo/addons/stock_orderpoint_manual_procurement/__manifest__.py
odoo/addons/stock_orderpoint_manual_procurement/demo/product.xml
odoo/addons/stock_orderpoint_manual_procurement/i18n/stock_orderpoint_manual_procurement.pot
odoo/addons/stock_orderpoint_manual_procurement/i18n/zh_CN.po
odoo/addons/stock_orderpoint_manual_procurement/models/__init__.py
odoo/addons/stock_orderpoint_manual_procurement/models/stock_warehouse_orderpoint.py
odoo/addons/stock_orderpoint_manual_procurement/readme/CONFIGURE.rst
odoo/addons/stock_orderpoint_manual_procurement/readme/CONTRIBUTORS.rst
odoo/addons/stock_orderpoint_manual_procurement/readme/DESCRIPTION.rst
odoo/addons/stock_orderpoint_manual_procurement/readme/USAGE.rst
odoo/addons/stock_orderpoint_manual_procurement/security/stock_orderpoint_manual_procurement_security.xml
odoo/addons/stock_orderpoint_manual_procurement/static/description/icon.png
odoo/addons/stock_orderpoint_manual_procurement/static/description/index.html
odoo/addons/stock_orderpoint_manual_procurement/tests/__init__.py
odoo/addons/stock_orderpoint_manual_procurement/tests/test_stock_orderpoint_manual_procurement.py
odoo/addons/stock_orderpoint_manual_procurement/views/stock_warehouse_orderpoint_view.xml
odoo/addons/stock_orderpoint_manual_procurement/wizards/__init__.py
odoo/addons/stock_orderpoint_manual_procurement/wizards/make_procurement_orderpoint.py
odoo/addons/stock_orderpoint_manual_procurement/wizards/make_procurement_orderpoint_view.xml
odoo13_addon_stock_orderpoint_manual_procurement-13.0.1.0.1.dist-info/METADATA
odoo13_addon_stock_orderpoint_manual_procurement-13.0.1.0.1.dist-info/WHEEL
odoo13_addon_stock_orderpoint_manual_procurement-13.0.1.0.1.dist-info/top_level.txt
odoo13_addon_stock_orderpoint_manual_procurement-13.0.1.0.1.dist-info/RECORD
