Metadata-Version: 2.1
Name: odoo13-addon-stock-orderpoint-manual-procurement
Version: 13.0.1.0.1
Summary: Allows to create procurement orders from orderpoints instead of relying only on the scheduler.
Home-page: https://github.com/OCA/stock-logistics-warehouse
Author: ForgeFlow, Odoo Community Association (OCA)
Author-email: support@odoo-community.org
License: AGPL-3
Platform: UNKNOWN
Classifier: Programming Language :: Python
Classifier: Framework :: Odoo
Classifier: License :: OSI Approved :: GNU Affero General Public License v3
Requires-Python: >=3.5
Requires-Dist: odoo (<13.1dev,>=13.0a)
